langchain_llm_utils/__init__.py
langchain_llm_utils/batch_process.py
langchain_llm_utils/benchmark_ratelimiter.py
langchain_llm_utils/common.py
langchain_llm_utils/config.py
langchain_llm_utils/evaluator.py
langchain_llm_utils/examples/text_analytics.py
langchain_llm_utils/llm.py
langchain_llm_utils/rate_limiter.py
langchain_llm_utils/request_cache.py
langchain_llm_utils/tests/test_batchprocess.py
langchain_llm_utils/tests/test_decider.py
langchain_llm_utils/tests/test_evaluator.py
langchain_llm_utils/tests/test_llm.py
langchain_llm_utils/tests/test_ratelimiter.py
langchain_llm_utils/tests/test_requestcache.py
langchain_llm_utils-0.1.2.dist-info/METADATA
langchain_llm_utils-0.1.2.dist-info/WHEEL
langchain_llm_utils-0.1.2.dist-info/RECORD
